dj_waff/__init__.py
dj_waff/apps.py
dj_waff/choice_with_other/__init__.py
dj_waff/choice_with_other/widget_compat.py
dj_waff/static/dj_waff/choice_with_other.js
dj_waff-0.1.2.dist-info/DESCRIPTION.rst
dj_waff-0.1.2.dist-info/METADATA
dj_waff-0.1.2.dist-info/RECORD
dj_waff-0.1.2.dist-info/WHEEL
dj_waff-0.1.2.dist-info/metadata.json
dj_waff-0.1.2.dist-info/top_level.txt
