Metadata-Version: 2.0
Name: dj-waff
Version: 0.1.2
Summary: dj_waff - A collection of extra Django Widgets and Form Fields
Home-page: https://github.com/luzfcb/dj_waff
Author: Fabio C. Barrionuevo da Luz
Author-email: bnafta@gmail.com
License: MIT
Keywords: dj_waff
Platform: UNKNOWN
Classifier: Development Status :: 3 - Alpha
Classifier: Framework :: Django
Classifier: Framework :: Django :: 1.8
Classifier: Intended Audience :: Developers
Classifier: License :: OSI Approved :: BSD License
Classifier: Natural Language :: English
Classifier: Programming Language :: Python :: 2
Classifier: Programming Language :: Python :: 2.7
Classifier: Programming Language :: Python :: 3
Classifier: Programming Language :: Python :: 3.4
Classifier: Programming Language :: Python :: 3.5
Classifier: Programming Language :: Python :: 3.6
